odoo/addons/purchase_sale_inter_company/README.rst
odoo/addons/purchase_sale_inter_company/__init__.py
odoo/addons/purchase_sale_inter_company/__manifest__.py
odoo/addons/purchase_sale_inter_company/i18n/de.po
odoo/addons/purchase_sale_inter_company/i18n/es.po
odoo/addons/purchase_sale_inter_company/i18n/fr.po
odoo/addons/purchase_sale_inter_company/i18n/fr_FR.po
odoo/addons/purchase_sale_inter_company/i18n/purchase_sale_inter_company.pot
odoo/addons/purchase_sale_inter_company/i18n/sl.po
odoo/addons/purchase_sale_inter_company/models/__init__.py
odoo/addons/purchase_sale_inter_company/models/account_invoice.py
odoo/addons/purchase_sale_inter_company/models/purchase_order.py
odoo/addons/purchase_sale_inter_company/models/res_company.py
odoo/addons/purchase_sale_inter_company/models/res_config.py
odoo/addons/purchase_sale_inter_company/models/sale_order.py
odoo/addons/purchase_sale_inter_company/models/stock_picking.py
odoo/addons/purchase_sale_inter_company/static/description/icon.png
odoo/addons/purchase_sale_inter_company/tests/__init__.py
odoo/addons/purchase_sale_inter_company/tests/inter_company_purchase_sale.xml
odoo/addons/purchase_sale_inter_company/tests/test_inter_company_purchase_sale.py
odoo/addons/purchase_sale_inter_company/views/purchase_order_view.xml
odoo/addons/purchase_sale_inter_company/views/res_company_view.xml
odoo/addons/purchase_sale_inter_company/views/res_config_view.xml
odoo11_addon_purchase_sale_inter_company-11.0.1.0.0.99.dev9.dist-info/METADATA
odoo11_addon_purchase_sale_inter_company-11.0.1.0.0.99.dev9.dist-info/WHEEL
odoo11_addon_purchase_sale_inter_company-11.0.1.0.0.99.dev9.dist-info/top_level.txt
odoo11_addon_purchase_sale_inter_company-11.0.1.0.0.99.dev9.dist-info/RECORD
